EnvBert/__init__.py
EnvBert/due_diligence.py
EnvBert/data/embeddings.csv
EnvBert-1.0.6.dist-info/METADATA
EnvBert-1.0.6.dist-info/WHEEL
EnvBert-1.0.6.dist-info/top_level.txt
EnvBert-1.0.6.dist-info/RECORD
