Metadata-Version: 2.1
Name: EnvBert
Version: 1.0.6
Summary: Predicts classes of environmental due diligence
Home-page: https://github.com/dreji18/environmental-due-diligence
Author: Afreen Aman, Deepak John Reji
Author-email: afreenaman90@gmail.com
License: MIT
Platform: UNKNOWN
Classifier: License :: OSI Approved :: MIT License
Classifier: Programming Language :: Python :: 3.6
Classifier: Programming Language :: Python :: 3.7
Classifier: Programming Language :: Python :: 3.8
Requires-Dist: numpy
Requires-Dist: transformers (==4.18.0)
Requires-Dist: tensorflow (==2.4.0)
Requires-Dist: sklearn
Requires-Dist: pandas
Requires-Dist: sentence-transformers (==2.2.0)
